morphik_rust-0.1.0.dist-info/METADATA
morphik_rust-0.1.0.dist-info/WHEEL
morphik_rust/__init__.py
morphik_rust/morphik_rust.cpython-311-darwin.so
morphik_rust-0.1.0.dist-info/RECORD
