Metadata-Version: 2.4
Name: morphik-rust
Version: 0.1.0
Classifier: Programming Language :: Rust
Classifier: Programming Language :: Python :: Implementation :: CPython
Classifier: Programming Language :: Python :: 3.10
Classifier: Programming Language :: Python :: 3.11
Classifier: Programming Language :: Python :: 3.12
Summary: High-performance Rust extensions for Morphik
Requires-Python: >=3.10
